{"statistics": {"evaluated_expectations": 23, "successful_expectations": 23, "unsuccessful_expectations": 0, "success_percent": 100.0}, "success": true, "results": [{"result": {"unexpected_percent": 0.0}, "success": true, "expectation_config": {"kwargs": {"column_list": ["pay_doc_type", "pay_doc_num"], "result_format": {"result_format": "SUMMARY", "partial_unexpected_count": 20}}, "expectation_type": "expect_compound_columns_to_be_unique", "meta": {}}, "meta": {}, "exception_info": {"raised_exception": false, "exception_message": null, "exception_traceback": null}}, {"result": {"element_count": 1000, "unexpected_count": 0, "unexpected_percent": 0.0, "unexpected_percent_total": 0.0, "partial_unexpected_list": []}, "success": true, "expectation_config": {"kwargs": {"column": "user_id", "result_format": {"result_format": "SUMMARY", "partial_unexpected_count": 20}}, "expectation_type": "expect_column_values_to_not_be_null", "meta": {}}, "meta": {}, "exception_info": {"raised_exception": false, "exception_message": null, "exception_traceback": null}}, {"result": {"observed_value": "INTEGER"}, "success": true, "expectation_config": {"kwargs": {"column": "user_id", "type_": "INTEGER", "result_format": {"result_format": "SUMMARY", "partial_unexpected_count": 20}}, "expectation_type": "expect_column_values_to_be_of_type", "meta": {}}, "meta": {}, "exception_info": {"raised_exception": false, "exception_message": null, "exception_traceback": null}}, {"result": {"element_count": 1000, "unexpected_count": 0, "unexpected_percent": 0.0, "unexpected_percent_total": 0.0, "partial_unexpected_list": []}, "success": true, "expectation_config": {"kwargs": {"column": "pay_doc_type", "result_format": {"result_format": "SUMMARY", "partial_unexpected_count": 20}}, "expectation_type": "expect_column_values_to_not_be_null", "meta": {}}, "meta": {}, "exception_info": {"raised_exception": false, "exception_message": null, "exception_traceback": null}}, {"result": {"observed_value": "TEXT"}, "success": true, "expectation_config": {"kwargs": {"column": "pay_doc_type", "type_": "TEXT", "result_format": {"result_format": "SUMMARY", "partial_unexpected_count": 20}}, "expectation_type": "expect_column_values_to_be_of_type", "meta": {}}, "meta": {}, "exception_info": {"raised_exception": false, "exception_message": null, "exception_traceback": null}}, {"result": {"observed_value": ["MASTER", "MIR", "VISA"], "element_count": 1000, "missing_count": null, "missing_percent": null, "details": {"value_counts": [{"value": "MASTER", "count": 352}, {"value": "MIR", "count": 334}, {"value": "VISA", "count": 314}]}}, "success": true, "expectation_config": {"kwargs": {"column": "pay_doc_type", "value_set": ["MASTER", "MIR", "VISA"], "result_format": {"result_format": "SUMMARY", "partial_unexpected_count": 20}}, "expectation_type": "expect_column_distinct_values_to_be_in_set", "meta": {}}, "meta": {}, "exception_info": {"raised_exception": false, "exception_message": null, "exception_traceback": null}}, {"result": {"observed_value": ["MASTER", "MIR", "VISA"], "element_count": 1000, "missing_count": null, "missing_percent": null, "details": {"value_counts": [{"value": "MASTER", "count": 352}, {"value": "MIR", "count": 334}, {"value": "VISA", "count": 314}]}}, "success": true, "expectation_config": {"kwargs": {"column": "pay_doc_type", "value_set": ["MASTER", "MIR", "VISA"], "result_format": {"result_format": "SUMMARY", "partial_unexpected_count": 20}}, "expectation_type": "expect_column_distinct_values_to_equal_set", "meta": {}}, "meta": {}, "exception_info": {"raised_exception": false, "exception_message": null, "exception_traceback": null}}, {"result": {"element_count": 1000, "unexpected_count": 0, "unexpected_percent": 0.0, "unexpected_percent_total": 0.0, "partial_unexpected_list": []}, "success": true, "expectation_config": {"kwargs": {"column": "pay_doc_num", "result_format": {"result_format": "SUMMARY", "partial_unexpected_count": 20}}, "expectation_type": "expect_column_values_to_not_be_null", "meta": {}}, "meta": {}, "exception_info": {"raised_exception": false, "exception_message": null, "exception_traceback": null}}, {"result": {"observed_value": "INTEGER"}, "success": true, "expectation_config": {"kwargs": {"column": "pay_doc_num", "type_": "INTEGER", "result_format": {"result_format": "SUMMARY", "partial_unexpected_count": 20}}, "expectation_type": "expect_column_values_to_be_of_type", "meta": {}}, "meta": {}, "exception_info": {"raised_exception": false, "exception_message": null, "exception_traceback": null}}, {"result": {"element_count": 1000, "unexpected_count": 0, "unexpected_percent": 0.0, "unexpected_percent_total": 0.0, "partial_unexpected_list": []}, "success": true, "expectation_config": {"kwargs": {"column": "account", "result_format": {"result_format": "SUMMARY", "partial_unexpected_count": 20}}, "expectation_type": "expect_column_values_to_not_be_null", "meta": {}}, "meta": {}, "exception_info": {"raised_exception": false, "exception_message": null, "exception_traceback": null}}, {"result": {"observed_value": "TEXT"}, "success": true, "expectation_config": {"kwargs": {"column": "account", "type_": "TEXT", "result_format": {"result_format": "SUMMARY", "partial_unexpected_count": 20}}, "expectation_type": "expect_column_values_to_be_of_type", "meta": {}}, "meta": {}, "exception_info": {"raised_exception": false, "exception_message": null, "exception_traceback": null}}, {"result": {"element_count": 1000, "missing_count": 0, "missing_percent": 0.0, "unexpected_count": 0, "unexpected_percent": 0.0, "unexpected_percent_total": 0.0, "unexpected_percent_nonmissing": 0.0, "partial_unexpected_list": [], "partial_unexpected_index_list": null, "partial_unexpected_counts": []}, "success": true, "expectation_config": {"kwargs": {"column": "account", "regex": "^FL-\\d+$", "result_format": {"result_format": "SUMMARY", "partial_unexpected_count": 20}}, "expectation_type": "expect_column_values_to_match_regex", "meta": {}}, "meta": {}, "exception_info": {"raised_exception": false, "exception_message": null, "exception_traceback": null}}, {"result": {"observed_value": "NUMERIC"}, "success": true, "expectation_config": {"kwargs": {"column": "phone", "type_": "NUMERIC", "result_format": {"result_format": "SUMMARY", "partial_unexpected_count": 20}}, "expectation_type": "expect_column_values_to_be_of_type", "meta": {}}, "meta": {}, "exception_info": {"raised_exception": false, "exception_message": null, "exception_traceback": null}}, {"result": {"element_count": 1000, "missing_count": 0, "missing_percent": 0.0, "unexpected_count": 0, "unexpected_percent": 0.0, "unexpected_percent_total": 0.0, "unexpected_percent_nonmissing": 0.0, "partial_unexpected_list": [], "partial_unexpected_index_list": null, "partial_unexpected_counts": []}, "success": true, "expectation_config": {"kwargs": {"column": "phone", "max_value": 79999999999, "min_value": 70000000000, "result_format": {"result_format": "SUMMARY", "partial_unexpected_count": 20}}, "expectation_type": "expect_column_values_to_be_between", "meta": {}}, "meta": {}, "exception_info": {"raised_exception": false, "exception_message": null, "exception_traceback": null}}, {"result": {"element_count": 1000, "unexpected_count": 0, "unexpected_percent": 0.0, "unexpected_percent_total": 0.0, "partial_unexpected_list": []}, "success": true, "expectation_config": {"kwargs": {"column": "billing_period", "result_format": {"result_format": "SUMMARY", "partial_unexpected_count": 20}}, "expectation_type": "expect_column_values_to_not_be_null", "meta": {}}, "meta": {}, "exception_info": {"raised_exception": false, "exception_message": null, "exception_traceback": null}}, {"result": {"observed_value": "DATE"}, "success": true, "expectation_config": {"kwargs": {"column": "billing_period", "type_": "DATE", "result_format": {"result_format": "SUMMARY", "partial_unexpected_count": 20}}, "expectation_type": "expect_column_values_to_be_of_type", "meta": {}}, "meta": {}, "exception_info": {"raised_exception": false, "exception_message": null, "exception_traceback": null}}, {"result": {"element_count": 1000, "missing_count": 0, "missing_percent": 0.0, "unexpected_count": 0, "unexpected_percent": 0.0, "unexpected_percent_total": 0.0, "unexpected_percent_nonmissing": 0.0, "partial_unexpected_list": [], "partial_unexpected_index_list": null, "partial_unexpected_counts": []}, "success": true, "expectation_config": {"kwargs": {"column": "billing_period", "max_value": "2022-01-01", "min_value": "2012-01-01", "result_format": {"result_format": "SUMMARY", "partial_unexpected_count": 20}}, "expectation_type": "expect_column_values_to_be_between", "meta": {}}, "meta": {}, "exception_info": {"raised_exception": false, "exception_message": null, "exception_traceback": null}}, {"result": {"element_count": 1000, "unexpected_count": 0, "unexpected_percent": 0.0, "unexpected_percent_total": 0.0, "partial_unexpected_list": []}, "success": true, "expectation_config": {"kwargs": {"column": "pay_date", "result_format": {"result_format": "SUMMARY", "partial_unexpected_count": 20}}, "expectation_type": "expect_column_values_to_not_be_null", "meta": {}}, "meta": {}, "exception_info": {"raised_exception": false, "exception_message": null, "exception_traceback": null}}, {"result": {"observed_value": "DATE"}, "success": true, "expectation_config": {"kwargs": {"column": "pay_date", "type_": "DATE", "result_format": {"result_format": "SUMMARY", "partial_unexpected_count": 20}}, "expectation_type": "expect_column_values_to_be_of_type", "meta": {}}, "meta": {}, "exception_info": {"raised_exception": false, "exception_message": null, "exception_traceback": null}}, {"result": {"element_count": 1000, "missing_count": 0, "missing_percent": 0.0, "unexpected_count": 0, "unexpected_percent": 0.0, "unexpected_percent_total": 0.0, "unexpected_percent_nonmissing": 0.0, "partial_unexpected_list": [], "partial_unexpected_index_list": null, "partial_unexpected_counts": []}, "success": true, "expectation_config": {"kwargs": {"column": "pay_date", "max_value": "2022-01-01", "min_value": "2012-01-01", "result_format": {"result_format": "SUMMARY", "partial_unexpected_count": 20}}, "expectation_type": "expect_column_values_to_be_between", "meta": {}}, "meta": {}, "exception_info": {"raised_exception": false, "exception_message": null, "exception_traceback": null}}, {"result": {"element_count": 1000, "unexpected_count": 0, "unexpected_percent": 0.0, "unexpected_percent_total": 0.0, "partial_unexpected_list": []}, "success": true, "expectation_config": {"kwargs": {"column": "sum", "result_format": {"result_format": "SUMMARY", "partial_unexpected_count": 20}}, "expectation_type": "expect_column_values_to_not_be_null", "meta": {}}, "meta": {}, "exception_info": {"raised_exception": false, "exception_message": null, "exception_traceback": null}}, {"result": {"observed_value": "INTEGER"}, "success": true, "expectation_config": {"kwargs": {"column": "sum", "type_": "INTEGER", "result_format": {"result_format": "SUMMARY", "partial_unexpected_count": 20}}, "expectation_type": "expect_column_values_to_be_of_type", "meta": {}}, "meta": {}, "exception_info": {"raised_exception": false, "exception_message": null, "exception_traceback": null}}, {"result": {"element_count": 1000, "missing_count": 0, "missing_percent": 0.0, "unexpected_count": 0, "unexpected_percent": 0.0, "unexpected_percent_total": 0.0, "unexpected_percent_nonmissing": 0.0, "partial_unexpected_list": [], "partial_unexpected_index_list": null, "partial_unexpected_counts": []}, "success": true, "expectation_config": {"kwargs": {"column": "sum", "max_value": 99999999, "min_value": 0, "result_format": {"result_format": "SUMMARY", "partial_unexpected_count": 20}}, "expectation_type": "expect_column_values_to_be_between", "meta": {}}, "meta": {}, "exception_info": {"raised_exception": false, "exception_message": null, "exception_traceback": null}}], "meta": {"great_expectations_version": "0.13.14", "expectation_suite_name": "izykov.ods_payment.warning", "run_id": {"run_time": "2021-05-24T14:25:40.375868+00:00", "run_name": "20210524T142540.375868Z"}, "batch_kwargs": {"data_asset_name": "izykov.ods_payment", "datasource": "greplu", "limit": 1000, "schema": "izykov", "table": "p_ods_payment"}, "batch_markers": {"ge_load_time": "20210524T142539.262781Z"}, "batch_parameters": null, "validation_time": "20210524T142540.411853Z"}, "evaluation_parameters": {}}